htutil/__init__.py
htutil/cache.py
htutil/counter.py
htutil/file.py
htutil-3.2.0.dist-info/LICENSE
htutil-3.2.0.dist-info/METADATA
htutil-3.2.0.dist-info/WHEEL
htutil-3.2.0.dist-info/top_level.txt
htutil-3.2.0.dist-info/RECORD
