Metadata-Version: 2.1
Name: htutil
Version: 3.2.0
Summary: HaoTian's Python Util
Home-page: https://github.com/117503445/htutil
Author: 117503445
Author-email: t117503445@gmail.com
Classifier: Programming Language :: Python :: 3
Classifier: License :: OSI Approved :: GNU General Public License v3 (GPLv3)
Classifier: Operating System :: OS Independent
License-File: LICENSE
Requires-Dist: pyyaml
